Metadata-Version: 2.1
Name: strings-from-file
Version: 0.1
Summary: Get strings from file and rewrite file
Author-email: nazarkalashnikovkalashnikov@yandex.ru
License: UNKNOWN
Platform: UNKNOWN
